LICENSE
MANIFEST.in
README
README.md
req.py
setup.py
with_redis.py
with_sql.py
oauth1/__init__.py
oauth1/authorize.py
oauth1_provider.egg-info/PKG-INFO
oauth1_provider.egg-info/SOURCES.txt
oauth1_provider.egg-info/dependency_links.txt
oauth1_provider.egg-info/not-zip-safe
oauth1_provider.egg-info/requires.txt
oauth1_provider.egg-info/top_level.txt
tests/sqlstore_tests.py
tests/sqlstore_tests.pyc