Metadata-Version: 1.0
Name: oauth1-provider
Version: 0.4.10
Summary: OAuth 1.0a Provider for Python
Home-page: https://github.com/tistaharahap/oauth1-provider/
Author: Batista Harahap
Author-email: batista@bango29.com
License: MIT
Keywords: oauth xauth provider
Platform: UNKNOWN
